README.md
setup.cfg
setup.py
grafana_inviter/__init__.py
grafana_inviter/accounts.py
grafana_inviter/cli.py
grafana_inviter/config_schema.py
grafana_inviter/grafana.py
grafana_inviter.egg-info/PKG-INFO
grafana_inviter.egg-info/SOURCES.txt
grafana_inviter.egg-info/dependency_links.txt
grafana_inviter.egg-info/entry_points.txt
grafana_inviter.egg-info/not-zip-safe
grafana_inviter.egg-info/requires.txt
grafana_inviter.egg-info/top_level.txt