Metadata-Version: 2.1
Name: grafana-inviter
Version: 0.0.5
Summary: Python module and script to invite people fetched from LDAP to Grafana
Home-page: https://github.com/tomtom-international/grafana-inviter
Author: Martin Migasiewicz
Author-email: migasiew.nk@gmail.com
License: Apache 2.0
Platform: UNKNOWN
Classifier: Programming Language :: Python :: 3
Classifier: Intended Audience :: Developers
Classifier: Environment :: Console
Classifier: Operating System :: OS Independent
Requires-Python: >3.5
